setup.py
gcc_subnets/__init__.py
gcc_subnets/subnets.py
gcc_subnets.egg-info/PKG-INFO
gcc_subnets.egg-info/SOURCES.txt
gcc_subnets.egg-info/dependency_links.txt
gcc_subnets.egg-info/not-zip-safe
gcc_subnets.egg-info/requires.txt
gcc_subnets.egg-info/top_level.txt